mongo_diff/__init__.py
mongo_diff/mongo_diff.py
mongo_diff-0.1.6.dist-info/METADATA
mongo_diff-0.1.6.dist-info/WHEEL
mongo_diff-0.1.6.dist-info/entry_points.txt
mongo_diff-0.1.6.dist-info/RECORD
