Metadata-Version: 2.1
Name: mongo-diff
Version: 0.1.6
Summary: Compare MongoDB collections from the command line.
Home-page: https://github.com/eecavanna/mongo-diff
Keywords: mongodb,mongo,diff,compare,collection,database,data
Requires-Python: >=3.10,<4.0
Classifier: Programming Language :: Python :: 3
Classifier: Programming Language :: Python :: 3.10
Classifier: Programming Language :: Python :: 3.11
Classifier: Programming Language :: Python :: 3.12
Requires-Dist: dictdiffer (>=0.9.0,<0.10.0)
Requires-Dist: pymongo (>=4.6.1,<5.0.0)
Requires-Dist: rich (>=13.7.0,<14.0.0)
Requires-Dist: typer (>=0.9.0,<0.10.0)
Project-URL: Documentation, https://github.com/eecavanna/mongo-diff
Project-URL: Repository, https://github.com/eecavanna/mongo-diff
